[{"name":"Arnold Palmer","ingredients":[{"tankId":0,"parts":1},{"tankId":"1","parts":1}],"id":22},{"name":"Vodka Lemonade","ingredients":[{"tankId":0,"parts":3},{"tankId":"2","parts":1}],"id":23},{"name":"Rum and Coke","ingredients":[{"tankId":"5","parts":2},{"tankId":"4","parts":1}],"id":24},{"name":"Summer Drink","ingredients":[{"tankId":"1","parts":2},{"tankId":0,"parts":1},{"tankId":"2","parts":1}],"id":25},{"name":"fdsasfshjgg","ingredients":[{"tankId":0,"parts":1},{"tankId":"1","parts":1}],"id":26}]